geneticalgorithm2/__init__.py
geneticalgorithm2/crossovers.py
geneticalgorithm2/geneticalgorithm2.py
geneticalgorithm2/mutations.py
geneticalgorithm2/population_initializer.py
geneticalgorithm2/selections.py
geneticalgorithm2/callbacks/__init__.py
geneticalgorithm2/callbacks/data.py
geneticalgorithm2/callbacks/middle.py
geneticalgorithm2/callbacks/simple.py
geneticalgorithm2/data_types/__init__.py
geneticalgorithm2/data_types/algorithm_params.py
geneticalgorithm2/data_types/aliases.py
geneticalgorithm2/data_types/base.py
geneticalgorithm2/data_types/generation.py
geneticalgorithm2/data_types/result.py
geneticalgorithm2/utils/__init__.py
geneticalgorithm2/utils/aliases.py
geneticalgorithm2/utils/cache.py
geneticalgorithm2/utils/files.py
geneticalgorithm2/utils/funcs.py
geneticalgorithm2/utils/plotting.py
geneticalgorithm2-6.9.2.dist-info/LICENSE
geneticalgorithm2-6.9.2.dist-info/METADATA
geneticalgorithm2-6.9.2.dist-info/WHEEL
geneticalgorithm2-6.9.2.dist-info/top_level.txt
geneticalgorithm2-6.9.2.dist-info/RECORD
