Metadata-Version: 2.1
Name: geneticalgorithm2
Version: 6.9.2
Summary: Supported highly optimized and flexible genetic algorithm package for python
Home-page: https://github.com/PasaOpasen/geneticalgorithm2
Author: Demetry Pascal
Author-email: qtckpuhdsa@gmail.com
Maintainer: Demetry Pascal
License: MIT
Keywords: solve,solver,equation,optimization,problem,genetic,algorithm,GA,easy,fast,genetic-algorithm,combinatorial,mixed,evolutionary
Classifier: Programming Language :: Python :: 3.8
Classifier: License :: OSI Approved :: MIT License
Classifier: Operating System :: OS Independent
Classifier: Topic :: Software Development :: Libraries :: Python Modules
Provides-Extra: full
License-File: LICENSE
